aiotus/__init__.py
aiotus/__main__.py
aiotus/common.py
aiotus/core.py
aiotus/creation.py
aiotus/entrypoint.py
aiotus/log.py
aiotus/py.typed
aiotus/retry.py
aiotus-1.1.0.dist-info/licenses/LICENSE.txt
aiotus-1.1.0.dist-info/METADATA
aiotus-1.1.0.dist-info/WHEEL
aiotus-1.1.0.dist-info/top_level.txt
aiotus-1.1.0.dist-info/RECORD
