Metadata-Version: 2.4
Name: aiotus
Version: 1.1.0
Summary: Asynchronous tus (tus.io) client library
Author-email: Jens Steinhauser <jens.steinhauser@gmail.com>
License: Apache-2.0
Project-URL: Homepage, https://github.com/JenSte/aiotus
Project-URL: Documentation, https://aiotus.readthedocs.io
Classifier: Programming Language :: Python :: 3
Classifier: Programming Language :: Python :: 3.10
Classifier: Programming Language :: Python :: 3.11
Classifier: Programming Language :: Python :: 3.12
Classifier: Programming Language :: Python :: 3.13
Classifier: Programming Language :: Python :: 3.14
Classifier: License :: OSI Approved :: Apache Software License
Classifier: Operating System :: OS Independent
Classifier: Topic :: Internet :: WWW/HTTP
Classifier: Typing :: Typed
Requires-Python: >=3.10
License-File: LICENSE.txt
Requires-Dist: aiohttp
Requires-Dist: tenacity>=6.2.0
Dynamic: license-file
